hrprotoparser/__init__.py
hrprotoparser/cli.py
hrprotoparser/protocol_parser.py
hrprotoparser-0.1.dev1.dist-info/METADATA
hrprotoparser-0.1.dev1.dist-info/WHEEL
hrprotoparser-0.1.dev1.dist-info/entry_points.txt
hrprotoparser-0.1.dev1.dist-info/top_level.txt
hrprotoparser-0.1.dev1.dist-info/RECORD
