Metadata-Version: 2.1
Name: hrprotoparser
Version: 0.1.dev1
Summary: Human Readable protocol parser
Home-page: https://github.com/hl037/hrprotoparser
Author: Léo Flaventin Hauchecorne
Author-email: hl037.prog@gmail.com
License: GPLv3
Platform: UNKNOWN
Requires-Dist: skbs
